momopy-0.0.5.dist-info/licenses/LICENSE
mtn/__init__.py
mtn/base.py
mtn/sandbox/__init__.py
mtn/sandbox/sandbox.py
telecel/__init__.py
telecel/base.py
momopy-0.0.5.dist-info/METADATA
momopy-0.0.5.dist-info/WHEEL
momopy-0.0.5.dist-info/top_level.txt
momopy-0.0.5.dist-info/RECORD
