Metadata-Version: 2.4
Name: momopy
Version: 0.0.5
Summary: Python wrapper for Mobile Money Providers
Home-page: https://github.com/sharhan-alhassan/momopy
Author: Sharhan Alhassan
Author-email: sharhanalhassan@gmail.com
Keywords: momo mobile-money python package library
Classifier: Programming Language :: Python :: 3
Classifier: License :: OSI Approved :: MIT License
Classifier: Operating System :: OS Independent
Requires-Python: >=3.9
License-File: LICENSE
Requires-Dist: certifi==2025.8.3
Requires-Dist: charset-normalizer==3.4.3
Requires-Dist: idna==3.10
Requires-Dist: python-dotenv==1.1.1
Requires-Dist: requests==2.32.5
Requires-Dist: urllib3==2.5.0
Dynamic: author
Dynamic: author-email
Dynamic: classifier
Dynamic: description
Dynamic: description-content-type
Dynamic: home-page
Dynamic: keywords
Dynamic: license-file
Dynamic: requires-dist
Dynamic: requires-python
Dynamic: summary
